Metadata-Version: 2.4
Name: mcp-server-test123
Version: 0.1.0
Summary: 一个使用 FastMCP 构建的示例服务器
Author-email: Your Name <you@example.com>
License: MIT
Classifier: Programming Language :: Python :: 3
Classifier: License :: OSI Approved :: MIT License
Classifier: Operating System :: OS Independent
Requires-Python: >=3.10
Requires-Dist: fastmcp>=2.10.1
Requires-Dist: pyotp>=2.9.0
Requires-Dist: pytz>=2025.2
Requires-Dist: tavily-python>=0.7.9
